MANIFEST.in
README.rst
setup.py
codelgb.egg-info/PKG-INFO
codelgb.egg-info/SOURCES.txt
codelgb.egg-info/dependency_links.txt
codelgb.egg-info/top_level.txt
codelgb/LightGBM/.appveyor.yml
codelgb/LightGBM/.gitignore
codelgb/LightGBM/.gitmodules
codelgb/LightGBM/.travis.yml
codelgb/LightGBM/.vsts-ci.yml
codelgb/LightGBM/CMakeLists.txt
codelgb/LightGBM/CODE_OF_CONDUCT.md
codelgb/LightGBM/LICENSE
codelgb/LightGBM/README.md
codelgb/LightGBM/VERSION.txt
codelgb/LightGBM/build_r.R
codelgb/LightGBM/.ci/setup.sh
codelgb/LightGBM/.ci/test.sh
codelgb/LightGBM/.ci/test_windows.ps1
codelgb/LightGBM/.ci/dockers/ubuntu-14.04/Dockerfile
codelgb/LightGBM/.git/HEAD
codelgb/LightGBM/.git/config
codelgb/LightGBM/.git/description
codelgb/LightGBM/.git/index
codelgb/LightGBM/.git/packed-refs
codelgb/LightGBM/.git/hooks/applypatch-msg.sample
codelgb/LightGBM/.git/hooks/commit-msg.sample
codelgb/LightGBM/.git/hooks/fsmonitor-watchman.sample
codelgb/LightGBM/.git/hooks/post-update.sample
codelgb/LightGBM/.git/hooks/pre-applypatch.sample
codelgb/LightGBM/.git/hooks/pre-commit.sample
codelgb/LightGBM/.git/hooks/pre-push.sample
codelgb/LightGBM/.git/hooks/pre-rebase.sample
codelgb/LightGBM/.git/hooks/pre-receive.sample
codelgb/LightGBM/.git/hooks/prepare-commit-msg.sample
codelgb/LightGBM/.git/hooks/update.sample
codelgb/LightGBM/.git/info/exclude
codelgb/LightGBM/.git/logs/HEAD
codelgb/LightGBM/.git/logs/refs/heads/master
codelgb/LightGBM/.git/logs/refs/remotes/origin/HEAD
codelgb/LightGBM/.git/objects/pack/pack-f62ff288ed9ae88b7911b2bf0bf27f93645a8bce.idx
codelgb/LightGBM/.git/objects/pack/pack-f62ff288ed9ae88b7911b2bf0bf27f93645a8bce.pack
codelgb/LightGBM/.git/refs/heads/master
codelgb/LightGBM/.git/refs/remotes/origin/HEAD
codelgb/LightGBM/.github/ISSUE_TEMPLATE.md
codelgb/LightGBM/.nuget/create_nuget.py
codelgb/LightGBM/R-package/.Rbuildignore
codelgb/LightGBM/R-package/DESCRIPTION
codelgb/LightGBM/R-package/LICENSE
codelgb/LightGBM/R-package/NAMESPACE
codelgb/LightGBM/R-package/README.md
codelgb/LightGBM/R-package/R/callback.R
codelgb/LightGBM/R-package/R/lgb.Booster.R
